setup.py
heliotron/__init__.py
heliotron/bridge.py
heliotron/light.py
heliotron/presets.py
heliotron/util.py
heliotron.egg-info/PKG-INFO
heliotron.egg-info/SOURCES.txt
heliotron.egg-info/dependency_links.txt
heliotron.egg-info/requires.txt
heliotron.egg-info/top_level.txt