Metadata-Version: 1.1
Name: heliotron
Version: 0.2.1
Summary: Simple library to interface with Philips Hue light bridges.
Home-page: https://github.com/briancline/heliotron
Author: Brian Cline
Author-email: brian.cline@gmail.com
License: MIT
Keywords: philips hue rest api light
Platform: UNKNOWN
Classifier: Development Status :: 3 - Alpha
Classifier: License :: OSI Approved :: MIT License
Classifier: Intended Audience :: Developers
Classifier: Operating System :: POSIX :: Linux
Classifier: Programming Language :: Python :: 2.7
Classifier: Topic :: Home Automation
